{"name":"","nickname":"","age":"Weight Class: Lightweight | Last Weigh-In: 155.5 lbs","heightReach":"Height: 5'8\" (173cm) | Reach: 68.0\" (173cm)","country":"Born: United States","record":"2-2-0","fights":{"pro":[{"mainInfo":"Loss · Corner Stoppage · 2:14 · R2","event":"Bellator 140","date":"2015.07.17","record":"2-1-0","card":"","timeFormat":"","weightClass":""},{"mainInfo":"Win · Guillotine Choke · 0:51 · R1","event":"Cage Titans 21","date":"2014.11.01","record":"1-1-0","card":"","timeFormat":"","weightClass":""},{"mainInfo":"Cancelled Bout","event":"","date":"2014.09.26","record":"","card":"","timeFormat":"","weightClass":""},{"mainInfo":"Win · Decision · Unanimous","event":"Reality Fighting","date":"2009.05.02","record":"0-1-0","card":"","timeFormat":"","weightClass":""},{"mainInfo":"No Contest · Accidental Eye Poke · 0:13 · R1","event":"Reality Fighting","date":"2009.01.17","record":"0-1-0","card":"","timeFormat":"","weightClass":""},{"mainInfo":"Loss","event":"World Fighting League","date":"2006.08.25","record":"","card":"","timeFormat":"","weightClass":""}],"am":[]}}