{"name":"","nickname":"","age":"Weight Class: Middleweight | Last Weigh-In: 194.0 lbs","heightReach":"Height: N/A | Reach: N/A","country":"Born: United States","record":"1-1-0","fights":{"pro":[],"am":[{"mainInfo":"Loss · KO/TKO · 2:34 · R3","event":"Cage Titans 41","date":"2018.11.03","record":"1-0-0","card":"","timeFormat":"","weightClass":""},{"mainInfo":"Win · Triangle Choke · 1:46 · R3","event":"Cage Titans 40","date":"2018.08.18","record":"0-0-0","card":"","timeFormat":"","weightClass":""},{"mainInfo":"Cancelled Bout","event":"","date":"2017.09.29","record":"","card":"","timeFormat":"","weightClass":""}]}}